odoo/addons/l10n_ch_qr_no_amount/README.rst
odoo/addons/l10n_ch_qr_no_amount/__init__.py
odoo/addons/l10n_ch_qr_no_amount/__manifest__.py
odoo/addons/l10n_ch_qr_no_amount/i18n/l10n_ch_qr_no_amount.pot
odoo/addons/l10n_ch_qr_no_amount/models/__init__.py
odoo/addons/l10n_ch_qr_no_amount/models/res_partner_bank.py
odoo/addons/l10n_ch_qr_no_amount/readme/CONTRIBUTORS.md
odoo/addons/l10n_ch_qr_no_amount/readme/CREDITS.md
odoo/addons/l10n_ch_qr_no_amount/readme/DESCRIPTION.md
odoo/addons/l10n_ch_qr_no_amount/readme/USAGE.md
odoo/addons/l10n_ch_qr_no_amount/report/__init__.py
odoo/addons/l10n_ch_qr_no_amount/report/swissqr_no_amount_report.py
odoo/addons/l10n_ch_qr_no_amount/report/swissqr_no_amount_report.xml
odoo/addons/l10n_ch_qr_no_amount/static/description/icon.png
odoo/addons/l10n_ch_qr_no_amount/static/description/index.html
odoo/addons/l10n_ch_qr_no_amount/static/src/img/Betragsfeld_Eckmarke.png
odoo/addons/l10n_ch_qr_no_amount/static/src/img/Feld_Betrag_40x15mm.png
odoo/addons/l10n_ch_qr_no_amount/static/src/scss/report_swissqr_no_amount.scss
odoo_addon_l10n_ch_qr_no_amount-17.0.1.0.0.2.dist-info/METADATA
odoo_addon_l10n_ch_qr_no_amount-17.0.1.0.0.2.dist-info/WHEEL
odoo_addon_l10n_ch_qr_no_amount-17.0.1.0.0.2.dist-info/top_level.txt
odoo_addon_l10n_ch_qr_no_amount-17.0.1.0.0.2.dist-info/RECORD
